ns_docker_wrapper/__init__.py
ns_docker_wrapper/commands.py
ns_docker_wrapper/manager.py
ns_docker_wrapper/py.typed
ns_docker_wrapper/utils.py
ns_docker_wrapper-0.1.2.dist-info/licenses/LICENSE
ns_docker_wrapper-0.1.2.dist-info/METADATA
ns_docker_wrapper-0.1.2.dist-info/WHEEL
ns_docker_wrapper-0.1.2.dist-info/top_level.txt
ns_docker_wrapper-0.1.2.dist-info/RECORD
