Metadata-Version: 2.4
Name: ns-docker-wrapper
Version: 0.1.2
Summary: Run Nerfstudio inside docker as a python package
Author-email: Jour de Lune <jourdelune863@gmail.com>
Project-URL: Homepage, https://github.com/jourdelune/ns_docker_wrapper
Project-URL: Repository, https://github.com/jourdelune/ns_docker_wrapper
Project-URL: Documentation, https://jourdelune.github.io/ns_docker_wrapper/
Requires-Python: >=3.10
License-File: LICENSE
Requires-Dist: docker>=7.1.0
Requires-Dist: pycolmap>=3.12.1
Dynamic: license-file
